{
  "policyName": "TA autotest chủ trương",
  "projectName": "TA autotest dự án",
  "lastPolicyName": "TA autotest chủ trương 0",
  "purchaseName": "TA autotest đề xuất mua sắm",
  "contractorPlanName": "TA autotest kế hoạch lựa chọn nhà thầu",
  "lastProjectName": "TA autotest dự án 1",
  "lastPurchaseName": "TA autotest đề xuất mua sắm 0",
  "selectionPlanName": "TA autotest kế hoạch lựa chọn nhà thầu",
  "lastSelectionPlanName": "TA autotest kế hoạch lựa chọn nhà thầu 0",
  "lastContractorName": "TA autotest 100",
  "listContractorInvest": [],
  "listContractorPurchase": [],
  "lastCostSubmissionName": "",
  "currentCostSubmissionName": "TA autotest tờ trình dự toán 0",
  "listPurchase": [],
  "listCostSubmission": []
}